faz-0.1.7.dist-info/RECORD
faz-0.1.7.dist-info/entry_points.txt
faz-0.1.7.dist-info/METADATA
faz-0.1.7.dist-info/WHEEL
faz-0.1.7.dist-info/metadata.json
faz-0.1.7.dist-info/top_level.txt
faz-0.1.7.dist-info/DESCRIPTION.rst
faz/task.py
faz/__init__.py
faz/graph.py
faz/main.py
faz/parser.py
