Metadata-Version: 2.0
Name: faz
Version: 0.1.7
Summary: "A Make-like tool with a syntax similar to Drake."
Home-page: https://github.com/hmartiniano/faz
Author: Hugo Martiniano
Author-email: hugomartiniano@gmail.com
License: BSD
Keywords: faz
Platform: UNKNOWN
Classifier: Development Status :: 2 - Pre-Alpha
Classifier: Environment :: Console
Classifier: Intended Audience :: Developers
Classifier: Topic :: Software Development :: Build Tools
Classifier: License :: OSI Approved :: BSD License
Classifier: Natural Language :: English
Classifier: Programming Language :: Python :: 2
Classifier: Programming Language :: Python :: 2.7
Classifier: Programming Language :: Python :: 3
Classifier: Programming Language :: Python :: 3.4
Classifier: Programming Language :: Python :: Implementation :: CPython
Classifier: Programming Language :: Python :: Implementation :: PyPy
Requires-Dist: argparse (==1.2.1)
Requires-Dist: decorator (==3.4.0)
Requires-Dist: wheel (==0.24.0)
